{
  "fetched_at": "2026-05-22T06:10:13Z",
  "total_count": 3,
  "unread_count": 1,
  "threads": [
    {
      "id": "19e443ed48d53bc5",
      "date": "2026-05-20T07:17:08Z",
      "isUnread": true,
      "classification": "other",
      "body": {
        "os_details": {
          "name": "chrome",
          "version": "148.0.0",
          "os": "Windows 10",
          "type": "browser"
        },
        "issue_text": "באחת התשובות ישנה שגיאת כתיב ",
        "user_details": {
          "roleType": [
            "Paid"
          ],
          "sub": "auth0|6a01eaf4a4398d1e91619573",
          "userId": "auth0|6a01eaf4a4398d1e91619573"
        },
        "extra_details": {
          "question_text": "כל הבאים מהווים גורם סיכון למחלת דלקת האגן (PID), פרט ל:",
          "right_answer": "אנדומטריטיס",
          "false_one": "ריבוי בני זוג  מיניים",
          "false_two": "תחילת פעילות מינית בגיל מוקדם",
          "false_three": "שטיפות וגינליות תכונות",
          "category": "סיעוד האישה",
          "division": "מצבים כלליים",
          "subdivision": "דלקת אגנית - PID",
          "level": "הבנה",
          "explanation": "גורמי סיכון לדלקת באגן (PID) :\n\t•\tנשים בגיל הפוריות, ובעיקר מתבגרות פעילות מינית\n\t•\tריבוי בני זוג מיניים\n\t•\tבן זוג עם היסטוריה של מספר רב של בני זוג\n\t•\tהיסטוריה קודמת של PID\n\t•\tתחילת פעילות מינית בגיל צעיר\n\t•\tהחדרת התקן תוך רחמי (IUD) לאחרונה\nהסיכון מוגבר בעיקר סביב תקופת ההחדרה, לא בגלל ההתקן עצמו אלא עקב האפשרות לזיהום חיידקי בעת ההחדרה.\n\t•\tשטיפות וגינליות קבועות (Douching)\n\nחשוב להדגיש:\nהתקן תוך רחמי (IUD) בפני עצמו אינו גורם ל-PID, אך התהליך של החדרת ההתקן עלול לגרום לזיהום וזאת בעיקר בתקופה הקרובה לאחר ההתקנה.\n\nגורמים מזהמים עיקריים ב-PID:\n\t•\tכלמידיה טרכומטיס (Chlamydia trachomatis)\n\t•\tנייסריה גונוריאה (Neisseria gonorrhoeae)\n\t•\tגורמים נוספים אפשריים: Gardnerella vaginalis, Haemophilus influenza, Streptococcus agalactiae.\n\nסיבוכים אפשריים לאחר PID:\n\t•\tאי פוריות\n\t•\tהריון חוץ רחמי (Ectopic pregnancy)\n\t•\tזיהומים כרוניים באגן\n\nהערה: PID יכולה להופיע לעיתים גם ללא תסמינים גלויים או עם ערכי מעבדה תקינים",
          "question_order": [
            "c",
            "b",
            "a",
            "d"
          ],
          "question_selection": "0",
          "status": "notSubmited",
          "question_number": 6,
          "question": {
            "question_id": "732c8c92-aaf3-418f-8919-3760ce3f3827",
            "question_text": "כל הבאים מהווים גורם סיכון למחלת דלקת האגן (PID), פרט ל:",
            "right_answer": "אנדומטריטיס",
            "false_one": "ריבוי בני זוג  מיניים",
            "false_two": "תחילת פעילות מינית בגיל מוקדם",
            "false_three": "שטיפות וגינליות תכונות",
            "attachment": "",
            "category": "סיעוד האישה",
            "division": "מצבים כלליים",
            "subdivision": "דלקת אגנית - PID",
            "level": "הבנה",
            "time_modified": "2025-03-07T06:50:05.135Z",
            "explanation": "גורמי סיכון לדלקת באגן (PID) :\n\t•\tנשים בגיל הפוריות, ובעיקר מתבגרות פעילות מינית\n\t•\tריבוי בני זוג מיניים\n\t•\tבן זוג עם היסטוריה של מספר רב של בני זוג\n\t•\tהיסטוריה קודמת של PID\n\t•\tתחילת פעילות מינית בגיל צעיר\n\t•\tהחדרת התקן תוך רחמי (IUD) לאחרונה\nהסיכון מוגבר בעיקר סביב תקופת ההחדרה, לא בגלל ההתקן עצמו אלא עקב האפשרות לזיהום חיידקי בעת ההחדרה.\n\t•\tשטיפות וגינליות קבועות (Douching)\n\nחשוב להדגיש:\nהתקן תוך רחמי (IUD) בפני עצמו אינו גורם ל-PID, אך התהליך של החדרת ההתקן עלול לגרום לזיהום וזאת בעיקר בתקופה הקרובה לאחר ההתקנה.\n\nגורמים מזהמים עיקריים ב-PID:\n\t•\tכלמידיה טרכומטיס (Chlamydia trachomatis)\n\t•\tנייסריה גונוריאה (Neisseria gonorrhoeae)\n\t•\tגורמים נוספים אפשריים: Gardnerella vaginalis, Haemophilus influenza, Streptococcus agalactiae.\n\nסיבוכים אפשריים לאחר PID:\n\t•\tאי פוריות\n\t•\tהריון חוץ רחמי (Ectopic pregnancy)\n\t•\tזיהומים כרוניים באגן\n\nהערה: PID יכולה להופיע לעיתים גם ללא תסמינים גלויים או עם ערכי מעבדה תקינים",
            "is_restoration": false,
            "restoration_cycle": null
          },
          "test_id": "6b54a444-6da1-45f4-b1ca-d3279c224b24",
          "user_id": "auth0|6a01eaf4a4398d1e91619573",
          "test_question_id": "2617b44f-60d8-4fc5-9a24-e3822368a741",
          "question_id": "732c8c92-aaf3-418f-8919-3760ce3f3827",
          "attachment": "",
          "time_modified": "2025-03-07T06:50:05.135Z",
          "is_restoration": false,
          "restoration_cycle": null
        }
      }
    },
    {
      "id": "19e4158e572dcb40",
      "date": "2026-05-19T17:46:44Z",
      "isUnread": false,
      "classification": "multiple",
      "body": {
        "os_details": {
          "name": "edge-chromium",
          "version": "148.0.0",
          "os": "Windows 10",
          "type": "browser"
        },
        "issue_text": "לדעתי כאן יש 2 תשובות נכונות- הגדלה והרחבה של העלייה הימנית + הגדלה משנית של החדר הימני. גם בתשובה כותבים משנית, ולכן מאוד מטעה..",
        "user_details": {
          "roleType": [
            "Paid"
          ],
          "sub": "auth0|6a01eacf964d9c202cb87926",
          "userId": "auth0|6a01eacf964d9c202cb87926"
        },
        "extra_details": {
          "question_text": "מהו הסיבוך ההמודינמי המשמעותי ביותר בחולים עם היצרות המסתם המיטרלי (Mitral Stenosis)?\n",
          "right_answer": "הגדלה והרחבה של העלייה השמאלית",
          "false_one": "הגדלה והרחבה של החדר השמאלי",
          "false_two": "הגדלה משנית של העלייה הימנית",
          "false_three": "הגדלה משנית של החדר הימני",
          "category": "סיעוד המבוגר",
          "division": "קרדיולוגיה",
          "subdivision": "בעיות מסתמים",
          "level": "הבנה",
          "explanation": "**תשובה נכונה**\nהגדלה והרחבה של העלייה השמאלית – בהיצרות המסתם המיטרלי עליונות העלים מתעבות ומתאחות, זרימת הדם מן העלייה אל החדר השמאלי נחסמת, לחץ בעלייה השמאלית עולה והעלייה מתרחבת; תהליך זה הוא הסיבוך ההמודינמי הראשוני והמשמעותי ביותר, וממנו נגזרות בהמשך יתר־לחץ ריאתי והיפרטרופיה של החדר הימני. \n\n**תשובות שגויות**\nהגדלה והרחבה של החדר השמאלי – בהיצרות מיטרלית נפח הדם המגיע לחדר השמאלי פוחת, ולכן החדר אינו מתרחב אלא אף עלול לקבל קדם-עומס נמוך ולתפקד בתפוקת לב ירודה; לפיכך אין זה סיבוך אופייני. \n\nהגדלה משנית של העלייה הימנית – השינוי המוביל במחלה הוא לחץ מוגבר במערכת הריאתית הגורם להיפרטרופיה של החדר הימני, לא להרחבת העלייה הימנית; לכן אפשרות זו איננה מתארת את הסיבוך המרכזי. \n\nהגדלה משנית של החדר הימני – אכן מתפתחת היפרטרופיה ימנית בשל יתר-לחץ ריאתי, אך היא מופיעה לאחר עליית הלחץ בעלייה השמאלית; לפיכך אין מדובר בסיבוך ההמודינמי הראשוני והחשוב ביותר אלא בתוצאה מאוחרת שלו. \n",
          "question_order": [
            "a",
            "d",
            "b",
            "c"
          ],
          "question_selection": "d",
          "status": "wrong",
          "question_number": 20,
          "question": {
            "question_id": "6c1c94ae-41b1-476e-98dd-3394d72a9d68",
            "question_text": "מהו הסיבוך ההמודינמי המשמעותי ביותר בחולים עם היצרות המסתם המיטרלי (Mitral Stenosis)?\n",
            "right_answer": "הגדלה והרחבה של העלייה השמאלית",
            "false_one": "הגדלה והרחבה של החדר השמאלי",
            "false_two": "הגדלה משנית של העלייה הימנית",
            "false_three": "הגדלה משנית של החדר הימני",
            "attachment": "",
            "category": "סיעוד המבוגר",
            "division": "קרדיולוגיה",
            "subdivision": "בעיות מסתמים",
            "level": "הבנה",
            "time_modified": "2025-06-17T18:10:30.022Z",
            "explanation": "**תשובה נכונה**\nהגדלה והרחבה של העלייה השמאלית – בהיצרות המסתם המיטרלי עליונות העלים מתעבות ומתאחות, זרימת הדם מן העלייה אל החדר השמאלי נחסמת, לחץ בעלייה השמאלית עולה והעלייה מתרחבת; תהליך זה הוא הסיבוך ההמודינמי הראשוני והמשמעותי ביותר, וממנו נגזרות בהמשך יתר־לחץ ריאתי והיפרטרופיה של החדר הימני. \n\n**תשובות שגויות**\nהגדלה והרחבה של החדר השמאלי – בהיצרות מיטרלית נפח הדם המגיע לחדר השמאלי פוחת, ולכן החדר אינו מתרחב אלא אף עלול לקבל קדם-עומס נמוך ולתפקד בתפוקת לב ירודה; לפיכך אין זה סיבוך אופייני. \n\nהגדלה משנית של העלייה הימנית – השינוי המוביל במחלה הוא לחץ מוגבר במערכת הריאתית הגורם להיפרטרופיה של החדר הימני, לא להרחבת העלייה הימנית; לכן אפשרות זו איננה מתארת את הסיבוך המרכזי. \n\nהגדלה משנית של החדר הימני – אכן מתפתחת היפרטרופיה ימנית בשל יתר-לחץ ריאתי, אך היא מופיעה לאחר עליית הלחץ בעלייה השמאלית; לפיכך אין מדובר בסיבוך ההמודינמי הראשוני והחשוב ביותר אלא בתוצאה מאוחרת שלו. \n",
            "is_restoration": true,
            "restoration_cycle": "ספטמבר 2024"
          },
          "test_id": "8fa17a79-542c-4548-8700-4d0510844ab0",
          "user_id": "auth0|6a01eacf964d9c202cb87926",
          "test_question_id": "5c01cc57-9a6f-419f-93de-1182e6a351f6",
          "question_id": "6c1c94ae-41b1-476e-98dd-3394d72a9d68",
          "attachment": "",
          "time_modified": "2025-06-17T18:10:30.022Z",
          "is_restoration": true,
          "restoration_cycle": "ספטמבר 2024"
        }
      }
    },
    {
      "id": "19e414f1c99fd6e3",
      "date": "2026-05-19T17:36:03Z",
      "isUnread": false,
      "classification": "explanation",
      "body": {
        "os_details": {
          "name": "edge-chromium",
          "version": "148.0.0",
          "os": "Windows 10",
          "type": "browser"
        },
        "issue_text": "בשאלה מבקשים סיבוך שהוא לא מיידי=סיבוך שמופיע מאוחר לאחר הצנטור. התשובה הנכונה לפיכם היא-סיבוכים וסקולריים מכיוון שדורשים ניטור לאחר הפעולה כדי שתהיה התערבות דחופה במקרה הצורך. לדעתי יש כאן טעות או חוסר דיוק בהסבר",
        "user_details": {
          "roleType": [
            "Paid"
          ],
          "sub": "auth0|6a01eacf964d9c202cb87926",
          "userId": "auth0|6a01eacf964d9c202cb87926"
        },
        "extra_details": {
          "question_text": "מה מהבאים נחשב כסיבוך לא מיידי לאחר צנתור לב (Cardiac Catheterization)?",
          "right_answer": "סיבוכים וסקולריים (Vascular complications)",
          "false_one": "הלם ספטי (Septic shock)",
          "false_two": "אי ספיקת כליות חריפה (Acute renal failure)",
          "false_three": "הפרעות קצב לב (Cardiac arrhythmias) ",
          "category": "סיעוד המבוגר",
          "division": "קרדיולוגיה",
          "subdivision": "צנתור לבבי",
          "level": "ידע",
          "explanation": "תשובה נכונה\nסיבוכים וסקולריים (Vascular complications) – צנתור לבבי עלול לגרום לסיבוכים וסקולריים כגון דימום עורקי, תסחיף (thromboembolism), היווצרות המטומה באתר הגישה, ודיסקציה של העורק. סיבוכים אלה עלולים להיות חמורים ודורשים ניטור צמוד לאחר הפעולה ובמקרים מסוימים גם התערבות דחופה.\n\nתשובות שגויות\nהפרעות קצב לב (Cardiac arrhythmias) – אמנם הפרעות קצב עלולות להתרחש במהלך או מיד לאחר הצנתור, אך הן פחות שכיחות לעומת סיבוכים וסקולריים ואינן מהוות את הקטגוריה המרכזית של סיבוכי הפעולה.\n\nהלם ספטי (Septic shock) – אינו סיבוך אופייני לצנתור לב אלא לסיבוכים זיהומיים חמורים אחרים, לרוב במצבים של זיהום מתקדם או ספסיס ממקור אחר.\n\nאי ספיקת כליות חריפה (Acute renal failure) – ייתכן כתוצאה מחשיפה לחומר ניגוד בצנתור, במיוחד במטופלים עם פגיעת כליות קודמת, אך זוהי תופעת לוואי פחות שכיחה ומניעתית יחסית (באמצעות הידרציה מוקדמת), ואינה מהווה את הסיבוך המרכזי המיידי או הנפוץ ביותר.\n",
          "question_order": [
            "c",
            "a",
            "d",
            "b"
          ],
          "question_selection": "b",
          "status": "wrong",
          "question_number": 12,
          "question": {
            "question_id": "af3235fc-fa3d-40a7-9482-7aa0570b9376",
            "question_text": "מה מהבאים נחשב כסיבוך לא מיידי לאחר צנתור לב (Cardiac Catheterization)?",
            "right_answer": "סיבוכים וסקולריים (Vascular complications)",
            "false_one": "הלם ספטי (Septic shock)",
            "false_two": "אי ספיקת כליות חריפה (Acute renal failure)",
            "false_three": "הפרעות קצב לב (Cardiac arrhythmias) ",
            "attachment": "",
            "category": "סיעוד המבוגר",
            "division": "קרדיולוגיה",
            "subdivision": "צנתור לבבי",
            "level": "ידע",
            "time_modified": "2025-08-31T23:11:33.397Z",
            "explanation": "תשובה נכונה\nסיבוכים וסקולריים (Vascular complications) – צנתור לבבי עלול לגרום לסיבוכים וסקולריים כגון דימום עורקי, תסחיף (thromboembolism), היווצרות המטומה באתר הגישה, ודיסקציה של העורק. סיבוכים אלה עלולים להיות חמורים ודורשים ניטור צמוד לאחר הפעולה ובמקרים מסוימים גם התערבות דחופה.\n\nתשובות שגויות\nהפרעות קצב לב (Cardiac arrhythmias) – אמנם הפרעות קצב עלולות להתרחש במהלך או מיד לאחר הצנתור, אך הן פחות שכיחות לעומת סיבוכים וסקולריים ואינן מהוות את הקטגוריה המרכזית של סיבוכי הפעולה.\n\nהלם ספטי (Septic shock) – אינו סיבוך אופייני לצנתור לב אלא לסיבוכים זיהומיים חמורים אחרים, לרוב במצבים של זיהום מתקדם או ספסיס ממקור אחר.\n\nאי ספיקת כליות חריפה (Acute renal failure) – ייתכן כתוצאה מחשיפה לחומר ניגוד בצנתור, במיוחד במטופלים עם פגיעת כליות קודמת, אך זוהי תופעת לוואי פחות שכיחה ומניעתית יחסית (באמצעות הידרציה מוקדמת), ואינה מהווה את הסיבוך המרכזי המיידי או הנפוץ ביותר.\n",
            "is_restoration": true,
            "restoration_cycle": "אפריל 2024"
          },
          "test_id": "8fa17a79-542c-4548-8700-4d0510844ab0",
          "user_id": "auth0|6a01eacf964d9c202cb87926",
          "test_question_id": "763e86ab-16aa-4e39-9b16-39c7fc132957",
          "question_id": "af3235fc-fa3d-40a7-9482-7aa0570b9376",
          "attachment": "",
          "time_modified": "2025-08-31T23:11:33.397Z",
          "is_restoration": true,
          "restoration_cycle": "אפריל 2024"
        }
      }
    }
  ]
}